LICENSE
tokelor/__init__.py
tokelor/__main__.py
tokelor/cli.py
tokelor-0.1.6.dist-info/entry_points.txt
tokelor-0.1.6.dist-info/LICENSE
tokelor-0.1.6.dist-info/WHEEL
tokelor-0.1.6.dist-info/METADATA
tokelor-0.1.6.dist-info/RECORD
