Metadata-Version: 2.1
Name: tokelor
Version: 0.1.6
Summary: Visualize Python token stream produced by tokenize module.
Home-page: https://github.com/lensvol/tokelor
License: MIT
Keywords: tokenize,tokens
Author: Kirill Borisov
Author-email: lensvol@gmail.com
Requires-Python: >=3.6,<4.0
Classifier: Development Status :: 4 - Beta
Classifier: Environment :: Console
Classifier: Intended Audience :: Developers
Classifier: License :: OSI Approved :: MIT License
Classifier: Operating System :: OS Independent
Classifier: Programming Language :: Python
Classifier: Programming Language :: Python :: 3
Classifier: Programming Language :: Python :: 3.6
Classifier: Programming Language :: Python :: 3.7
Classifier: Programming Language :: Python :: 3.8
Classifier: Topic :: Software Development
Classifier: Topic :: Software Development :: Quality Assurance
Classifier: Topic :: Utilities
Requires-Dist: click (>=7.0,<8.0)
Requires-Dist: colorama (>=0.4,<0.5)
Project-URL: Repository, https://github.com/lensvol/tokelor
